snap_python/__init__.py
snap_python/client.py
snap_python/components/__init__.py
snap_python/components/config.py
snap_python/components/snaps.py
snap_python/components/store.py
snap_python/schemas/changes.py
snap_python/schemas/common.py
snap_python/schemas/config.py
snap_python/schemas/snaps.py
snap_python/schemas/store/__init__.py
snap_python/schemas/store/categories.py
snap_python/schemas/store/info.py
snap_python/schemas/store/json/category_by_name_schema.json
snap_python/schemas/store/json/category_schema.json
snap_python/schemas/store/json/snaps_find_schema.json
snap_python/schemas/store/json/snaps_info_schema.json
snap_python/schemas/store/refresh.py
snap_python/schemas/store/search.py
snap_python/schemas/store/track.py
snap_python/scrape.py
snap_python/utils.py
snap_python-0.1.7.dist-info/LICENSE
snap_python-0.1.7.dist-info/METADATA
snap_python-0.1.7.dist-info/WHEEL
snap_python-0.1.7.dist-info/RECORD
