Metadata-Version: 2.3
Name: snap-python
Version: 0.1.7
Summary: Interact with snapd and snapstore(s) from Python
License: MIT
Author: Alexander Lukens
Author-email: alexdlukens@gmail.com
Requires-Python: >=3.10,<4.0
Classifier: License :: OSI Approved :: MIT License
Classifier: Programming Language :: Python :: 3
Classifier: Programming Language :: Python :: 3.10
Classifier: Programming Language :: Python :: 3.11
Classifier: Programming Language :: Python :: 3.12
Classifier: Programming Language :: Python :: 3.13
Requires-Dist: httpx (>0.27,<1)
Requires-Dist: pydantic (>2.9,<3)
Requires-Dist: retry (>=0.9.2,<0.10.0)
Project-URL: Documentation, https://alexdlukens.github.io/snap-python/
Project-URL: Repository, https://github.com/alexdlukens/snap-python
